leo/__init__.py
leo/algorithms/__init__.py
leo/algorithms/bfs.py
leoambrose-0.1.0.dist-info/licenses/LICENSE
leoambrose-0.1.0.dist-info/METADATA
leoambrose-0.1.0.dist-info/WHEEL
leoambrose-0.1.0.dist-info/top_level.txt
leoambrose-0.1.0.dist-info/RECORD
