Metadata-Version: 2.4
Name: leoambrose
Version: 0.1.0
Summary: Hehe Enjoy Mate
Home-page: https://github.com/vijaysharonl/leo
Author: vijaysharonl
Author-email: vijaysharonl2005@gmail.com
Classifier: Programming Language :: Python :: 3
Classifier: Programming Language :: Python :: 3.8
Classifier: Programming Language :: Python :: 3.9
Requires-Python: >=3.7
License-File: LICENSE
Dynamic: author
Dynamic: author-email
Dynamic: classifier
Dynamic: description-content-type
Dynamic: home-page
Dynamic: license-file
Dynamic: requires-python
Dynamic: summary
